agents/__init__.py
agents/core.py
agents/memory.py
integrations/__init__.py
integrations/pugins.py
models/__init__.py
models/gpt.py
utils/__init__.py
utils/encryption.py
utils/logging.py
my_ai_framework-0.1.0.dist-info/METADATA
my_ai_framework-0.1.0.dist-info/WHEEL
my_ai_framework-0.1.0.dist-info/entry_points.txt
my_ai_framework-0.1.0.dist-info/top_level.txt
my_ai_framework-0.1.0.dist-info/RECORD
