Metadata-Version: 2.2
Name: my_ai_framework
Version: 0.1.0
Requires-Dist: transformers
Requires-Dist: flask
Dynamic: requires-dist
